jtalkbot/__init__.py
jtalkbot/__main__.py
jtalkbot/openjtalk.py
jtalkbot-0.8.1.dist-info/LICENSE
jtalkbot-0.8.1.dist-info/METADATA
jtalkbot-0.8.1.dist-info/WHEEL
jtalkbot-0.8.1.dist-info/entry_points.txt
jtalkbot-0.8.1.dist-info/top_level.txt
jtalkbot-0.8.1.dist-info/RECORD
