Metadata-Version: 2.1
Name: jtalkbot
Version: 0.8.1
Summary: A discord bot talking Japanese.
Author-email: Masaaki Shibata <mshibata@emptypage.jp>
License: Copyright © 2020 Masaaki Shibata
Project-URL: Repository, https://bitbucket.org/emptypage/jtalkbot/
Keywords: discord
Classifier: Programming Language :: Python
Classifier: Programming Language :: Python :: 3
Classifier: Programming Language :: Python :: 3.10
Classifier: Programming Language :: Python :: 3.11
Classifier: Programming Language :: Python :: 3.12
Classifier: License :: OSI Approved :: MIT License
Classifier: Operating System :: OS Independent
Requires-Python: >=3.10
License-File: LICENSE
Requires-Dist: discord.py[voice]
Requires-Dist: python-dotenv
Provides-Extra: dev
Requires-Dist: build ; extra == 'dev'
Requires-Dist: setuptools-scm ; extra == 'dev'
Requires-Dist: twine ; extra == 'dev'
